{"totalResultsCount":4,"geonames":[{"adminCode1":"00","lng":"2","geonameId":3017382,"toponymName":"Republic of France","countryId":"3017382","fcl":"A","population":64768389,"countryCode":"FR","name":"France","fclName":"country, state, region,...","countryName":"France","fcodeName":"independent political entity","adminName1":"","lat":"46","fcode":"PCLI"},{"adminCode1":"00","lng":"10.5","geonameId":2921044,"toponymName":"Federal Republic of Germany","countryId":"2921044","fcl":"A","population":81802257,"countryCode":"DE","name":"Germany","fclName":"country, state, region,...","countryName":"Germany","fcodeName":"independent political entity","adminName1":"","lat":"51.5","fcode":"PCLI"},{"adminCode1":"00","lng":"6.16667","geonameId":2960313,"toponymName":"Grand Duchy of Luxembourg","countryId":"2960313","fcl":"A","population":497538,"countryCode":"LU","name":"Luxembourg","fclName":"country, state, region,...","countryName":"Luxembourg","fcodeName":"independent political entity","adminName1":"","lat":"49.75","fcode":"PCLI"},{"adminCode1":"00","lng":"5.75","geonameId":2750405,"toponymName":"Kingdom of the Netherlands","countryId":"2750405","fcl":"A","population":16645000,"countryCode":"NL","name":"Netherlands","fclName":"country, state, region,...","countryName":"Netherlands","fcodeName":"independent political entity","adminName1":"","lat":"52.25","fcode":"PCLI"}]}